odoo/addons/sale_stock_delivery_state/README.rst
odoo/addons/sale_stock_delivery_state/__init__.py
odoo/addons/sale_stock_delivery_state/__manifest__.py
odoo/addons/sale_stock_delivery_state/i18n/it.po
odoo/addons/sale_stock_delivery_state/i18n/pt.po
odoo/addons/sale_stock_delivery_state/i18n/sale_stock_delivery_state.pot
odoo/addons/sale_stock_delivery_state/models/__init__.py
odoo/addons/sale_stock_delivery_state/models/sale_order.py
odoo/addons/sale_stock_delivery_state/readme/CONTRIBUTORS.md
odoo/addons/sale_stock_delivery_state/readme/CREDITS.md
odoo/addons/sale_stock_delivery_state/readme/DESCRIPTION.md
odoo/addons/sale_stock_delivery_state/static/description/icon.png
odoo/addons/sale_stock_delivery_state/static/description/index.html
odoo/addons/sale_stock_delivery_state/views/sale_order_views.xml
odoo_addon_sale_stock_delivery_state-18.0.1.0.0.4.dist-info/METADATA
odoo_addon_sale_stock_delivery_state-18.0.1.0.0.4.dist-info/WHEEL
odoo_addon_sale_stock_delivery_state-18.0.1.0.0.4.dist-info/top_level.txt
odoo_addon_sale_stock_delivery_state-18.0.1.0.0.4.dist-info/RECORD
